{
  "name": "cfa-tofu-modules",
  "private": true,
  "repository": {
    "type": "git",
    "url": "git@github.com:codeforamerica/tofu-modules.git"
  },
  "devDependencies": {
    "@semantic-release/github": "~11.0",
    "semantic-release": "~24.1"
  },
  "release": {
    "branches": [
      "main",
      "module-release"
    ]
  },
  "plugins": [
    "@semantic-release/commit-analyzer",
    {
      "preset": "atom"
    },
    "@semantic-release/release-notes-generator",
    "@semantic-release/github"
  ]
}
